LICENSE.txt
MANIFEST.in
README.rst
setup.py
aldryn_style/__init__.py
aldryn_style/cms_plugins.py
aldryn_style/models.py
aldryn_style.egg-info/PKG-INFO
aldryn_style.egg-info/SOURCES.txt
aldryn_style.egg-info/dependency_links.txt
aldryn_style.egg-info/not-zip-safe
aldryn_style.egg-info/top_level.txt
aldryn_style/locale/ar/LC_MESSAGES/django.mo
aldryn_style/locale/ar/LC_MESSAGES/django.po
aldryn_style/locale/bg/LC_MESSAGES/django.mo
aldryn_style/locale/bg/LC_MESSAGES/django.po
aldryn_style/locale/ca/LC_MESSAGES/django.mo
aldryn_style/locale/ca/LC_MESSAGES/django.po
aldryn_style/locale/cs/LC_MESSAGES/django.mo
aldryn_style/locale/cs/LC_MESSAGES/django.po
aldryn_style/locale/da/LC_MESSAGES/django.mo
aldryn_style/locale/da/LC_MESSAGES/django.po
aldryn_style/locale/de/LC_MESSAGES/django.mo
aldryn_style/locale/de/LC_MESSAGES/django.po
aldryn_style/locale/el/LC_MESSAGES/django.mo
aldryn_style/locale/el/LC_MESSAGES/django.po
aldryn_style/locale/en/LC_MESSAGES/django.mo
aldryn_style/locale/en/LC_MESSAGES/django.po
aldryn_style/locale/es/LC_MESSAGES/django.mo
aldryn_style/locale/es/LC_MESSAGES/django.po
aldryn_style/locale/es_BO/LC_MESSAGES/django.mo
aldryn_style/locale/es_BO/LC_MESSAGES/django.po
aldryn_style/locale/et/LC_MESSAGES/django.mo
aldryn_style/locale/et/LC_MESSAGES/django.po
aldryn_style/locale/eu/LC_MESSAGES/django.mo
aldryn_style/locale/eu/LC_MESSAGES/django.po
aldryn_style/locale/fa/LC_MESSAGES/django.mo
aldryn_style/locale/fa/LC_MESSAGES/django.po
aldryn_style/locale/fi/LC_MESSAGES/django.mo
aldryn_style/locale/fi/LC_MESSAGES/django.po
aldryn_style/locale/fr/LC_MESSAGES/django.mo
aldryn_style/locale/fr/LC_MESSAGES/django.po
aldryn_style/locale/gl/LC_MESSAGES/django.mo
aldryn_style/locale/gl/LC_MESSAGES/django.po
aldryn_style/locale/gu/LC_MESSAGES/django.mo
aldryn_style/locale/gu/LC_MESSAGES/django.po
aldryn_style/locale/he/LC_MESSAGES/django.mo
aldryn_style/locale/he/LC_MESSAGES/django.po
aldryn_style/locale/hi/LC_MESSAGES/django.mo
aldryn_style/locale/hi/LC_MESSAGES/django.po
aldryn_style/locale/hr/LC_MESSAGES/django.mo
aldryn_style/locale/hr/LC_MESSAGES/django.po
aldryn_style/locale/hu/LC_MESSAGES/django.mo
